setup.py
django_geetar.egg-info/PKG-INFO
django_geetar.egg-info/SOURCES.txt
django_geetar.egg-info/dependency_links.txt
django_geetar.egg-info/requires.txt
django_geetar.egg-info/top_level.txt
geetar/__init__.py
geetar/fields.py
geetar/google_maps.py
geetar/models.py
geetar/paginator.py
geetar/test_settings.py
geetar/statusable/__init__.py
geetar/statusable/admin.py
geetar/statusable/models.py
geetar/templatetags/__init__.py
geetar/templatetags/geetar.py
geetar/tests/__init__.py
geetar/tests/base.py
geetar/tests/test_fields.py
geetar/tests/test_google_maps.py
geetar/tests/test_paginator.py
geetar/tests/test_statusable.py
geetar/tests/test_templatetags.py
test_app/__init__.py
test_app/models.py