Metadata-Version: 1.0
Name: django-geetar
Version: 1.0
Summary: A swiss army knife for your Django project, including a smattering of helpful code
Home-page: https://github.com/Instrument/django-geetar
Author: Instrument
Author-email: chris.forrette@weareinstrument.com
License: UNKNOWN
Keywords: django,helpers
Platform: UNKNOWN
Classifier: Framework :: Django
Classifier: Topic :: Internet
Classifier: License :: OSI Approved :: BSD License
Classifier: Intended Audience :: Developers
Classifier: Environment :: Web Environment
Classifier: Programming Language :: Python :: 2.5
Classifier: Programming Language :: Python :: 2.6
Classifier: Programming Language :: Python :: 2.7
